_bool_query/__init__.py
_bool_query/_base.py
_bool_query/_interface.py
_bool_query/_length_q.py
_bool_query/_numeric_q.py
_bool_query/_string_q.py
_bool_query/py.typed
_bool_query/_logical/__init__.py
_bool_query/_logical/_and.py
_bool_query/_logical/_mixin.py
_bool_query/_logical/_not.py
_bool_query/_logical/_or.py
light_types/__init__.py
light_types/_base.py
light_types/_light_type.py
light_types/_meta.py
light_types/_qlight_type.py
light_types/_utils.py
light_types/py.typed
light_types-1.2.2.dist-info/METADATA
light_types-1.2.2.dist-info/WHEEL
light_types-1.2.2.dist-info/licenses/LICENSE
light_types-1.2.2.dist-info/RECORD
