Metadata-Version: 2.3
Name: light-types
Version: 1.2.2
Summary: Parse, don't validate
Project-URL: Homepage, https://pypi.org/project/light-types/
Project-URL: Repository, https://github.com/likeinlife/light-types/
Author-email: likeinlife <likeinlife@outlook.com>
License-Expression: MIT
License-File: LICENSE
Keywords: phantom types,value object
Classifier: Intended Audience :: Developers
Classifier: License :: OSI Approved :: MIT License
Classifier: Operating System :: OS Independent
Classifier: Programming Language :: Python
Classifier: Programming Language :: Python :: 3 :: Only
Classifier: Programming Language :: Python :: 3.11
Classifier: Programming Language :: Python :: 3.12
Classifier: Programming Language :: Python :: 3.13
Classifier: Topic :: Software Development :: Libraries :: Python Modules
Requires-Python: >=3.11
Requires-Dist: pydantic>=2.8.2
